tinyhtml5/__init__.py
tinyhtml5/constants.py
tinyhtml5/inputstream.py
tinyhtml5/parser.py
tinyhtml5/tokenizer.py
tinyhtml5/treebuilder.py
tinyhtml5-2.0.0b1.dist-info/LICENSE
tinyhtml5-2.0.0b1.dist-info/WHEEL
tinyhtml5-2.0.0b1.dist-info/METADATA
tinyhtml5-2.0.0b1.dist-info/RECORD
